wqchartpy/BivariateColourScheme.npy
wqchartpy/__init__.py
wqchartpy/chadha.py
wqchartpy/chernoff.py
wqchartpy/color_piper.py
wqchartpy/contour_piper.py
wqchartpy/durvo.py
wqchartpy/gaillardet.py
wqchartpy/gibbs.py
wqchartpy/hfed.py
wqchartpy/ions.py
wqchartpy/rectangle_piper.py
wqchartpy/schoeller.py
wqchartpy/stiff.py
wqchartpy/triangle_piper.py
wqchartpy-0.1.10.dist-info/LICENSE
wqchartpy-0.1.10.dist-info/METADATA
wqchartpy-0.1.10.dist-info/WHEEL
wqchartpy-0.1.10.dist-info/top_level.txt
wqchartpy-0.1.10.dist-info/RECORD
