Metadata-Version: 2.1
Name: wqchartpy
Version: 0.1.10
Summary: Python Package for Visualization of Water Geochemistry Data
Home-page: https://www.github.com/jyangfsu/WQChartPy
Author: Jing Yang
Author-email: jingyang@cug.edu.cn
Maintainer: Jing Yang
Maintainer-email: jingyang@cug.edu.cn
License: GNU General Public License v3.0
Requires-Python: >=3.7
License-File: LICENSE
